dfuse/__init__.py
dfuse/config.py
dfuse/eosio/__init__.py
dfuse/eosio/core.py
dfuse/eosio/types.py
dfuse/eth/__init__.py
dfuse/eth/core.py
dfuse/eth/types.py
dfuse/ws/__init__.py
dfuse/ws/ws.py
dfuse-0.0.8.dist-info/COPYING
dfuse-0.0.8.dist-info/METADATA
dfuse-0.0.8.dist-info/WHEEL
dfuse-0.0.8.dist-info/top_level.txt
dfuse-0.0.8.dist-info/RECORD
