Metadata-Version: 2.1
Name: dfuse
Version: 0.0.8
Summary: Python wrapper around the dfuse.io API.
Home-page: https://github.com/chmod77/dfuse-python
Author: chmod77
Author-email: ch33s3codes@gmail.com
License: MIT License
Project-URL: Bug Reports, https://github.com/chmod77/dfuse-python/issues
Project-URL: Buy me a coffee, https://github.com/chmod77/dfuse-python#buy-me-a-coffee
Keywords: EOSIO,API,dfuse
Platform: UNKNOWN
Classifier: License :: OSI Approved :: MIT License
Classifier: Development Status :: 2 - Pre-Alpha
Classifier: Intended Audience :: Developers
Classifier: Programming Language :: Python
Classifier: Programming Language :: Python :: 3.5
Classifier: Programming Language :: Python :: 3.6
Classifier: Programming Language :: Python :: 3.7
Classifier: Programming Language :: Python :: 3.8
Classifier: Programming Language :: Python :: 3.9
Classifier: Topic :: Software Development :: Libraries :: Python Modules
Requires-Dist: requests (>=2.22.0)
Requires-Dist: requests-cache (>=0.5.2)
Requires-Dist: websockets (>=8.0.2)
Requires-Dist: grpcio (>=1.23.0)
Requires-Dist: grpcio-tools (>=1.23.0)
Requires-Dist: python-decouple (>=3.1)
